LICENSE
MANIFEST.in
README.md
setup.cfg
setup.py
versioneer.py
fenicsprecice/__init__.py
fenicsprecice/_version.py
fenicsprecice/adapter_core.py
fenicsprecice/config.py
fenicsprecice/expression_core.py
fenicsprecice/fenicsprecice.py
fenicsprecice/solverstate.py
fenicsprecice.egg-info/PKG-INFO
fenicsprecice.egg-info/SOURCES.txt
fenicsprecice.egg-info/dependency_links.txt
fenicsprecice.egg-info/not-zip-safe
fenicsprecice.egg-info/requires.txt
fenicsprecice.egg-info/top_level.txt