Metadata-Version: 2.1
Name: fenicsprecice
Version: 1.4.0
Summary: FEniCS-preCICE adapter is a preCICE adapter for the open source computing platform FEniCS.
Home-page: https://github.com/precice/fenics-adapter
Author: the preCICE developers
Author-email: info@precice.org
License: LGPL-3.0
License-File: LICENSE
